mycdp/__init__.py
mycdp/accessibility.py
mycdp/animation.py
mycdp/audits.py
mycdp/autofill.py
mycdp/background_service.py
mycdp/browser.py
mycdp/cache_storage.py
mycdp/cast.py
mycdp/console.py
mycdp/css.py
mycdp/database.py
mycdp/debugger.py
mycdp/device_access.py
mycdp/device_orientation.py
mycdp/dom.py
mycdp/dom_debugger.py
mycdp/dom_snapshot.py
mycdp/dom_storage.py
mycdp/emulation.py
mycdp/event_breakpoints.py
mycdp/extensions.py
mycdp/fed_cm.py
mycdp/fetch.py
mycdp/headless_experimental.py
mycdp/heap_profiler.py
mycdp/indexed_db.py
mycdp/input_.py
mycdp/inspector.py
mycdp/io.py
mycdp/layer_tree.py
mycdp/log.py
mycdp/media.py
mycdp/memory.py
mycdp/network.py
mycdp/overlay.py
mycdp/page.py
mycdp/performance.py
mycdp/performance_timeline.py
mycdp/preload.py
mycdp/profiler.py
mycdp/pwa.py
mycdp/py.typed
mycdp/runtime.py
mycdp/schema.py
mycdp/security.py
mycdp/service_worker.py
mycdp/storage.py
mycdp/system_info.py
mycdp/target.py
mycdp/tethering.py
mycdp/tracing.py
mycdp/util.py
mycdp/web_audio.py
mycdp/web_authn.py
mycdp-1.2.1.dist-info/licenses/LICENSE
mycdp-1.2.1.dist-info/METADATA
mycdp-1.2.1.dist-info/WHEEL
mycdp-1.2.1.dist-info/top_level.txt
mycdp-1.2.1.dist-info/RECORD
